tink_fpe/__init__.py
tink_fpe/_fpe.py
tink_fpe/_fpe_ff3.py
tink_fpe/_fpe_ffx_key_manager.py
tink_fpe/_fpe_key_templates.py
tink_fpe/_fpe_wrapper.py
tink_fpe/_util.py
tink_fpe/proto/__init__.py
tink_fpe/proto/fpe_ffx_pb2.py
tink_fpe/proto/fpe_ffx_pb2.pyi
tink_fpe/py.typed
tink_fpe-0.4.0.dist-info/LICENSE
tink_fpe-0.4.0.dist-info/METADATA
tink_fpe-0.4.0.dist-info/WHEEL
tink_fpe-0.4.0.dist-info/entry_points.txt
tink_fpe-0.4.0.dist-info/RECORD
