Metadata-Version: 2.1
Name: tink-fpe
Version: 0.4.0
Summary: Format-Preserving Encryption support for Google Tink
Home-page: https://github.com/statisticsnorway/tink-fpe-project
License: MIT
Author: Statistics Norway
Author-email: stat-dev@ssb.no
Requires-Python: >=3.8,<4.0
Classifier: Development Status :: 3 - Alpha
Classifier: License :: OSI Approved :: MIT License
Classifier: Programming Language :: Python :: 3
Classifier: Programming Language :: Python :: 3.8
Classifier: Programming Language :: Python :: 3.9
Classifier: Programming Language :: Python :: 3.10
Classifier: Programming Language :: Python :: 3.11
Requires-Dist: ff3 (>=1.0.1)
Requires-Dist: protobuf (>=3.20.1)
Requires-Dist: tink (>=1.7.0)
Requires-Dist: urllib3 (<2)
Project-URL: Changelog, https://github.com/statisticsnorway/tink-fpe-python/releases
Project-URL: Documentation, https://statisticsnorway.github.io/tink-fpe-project
Project-URL: Repository, https://github.com/statisticsnorway/tink-fpe-python
